itng/__init__.py
itng/drawing.py
itng/graphUtility.py
itng/modules.py
itng/networks.py
itng/randomGenerators.py
itng/randomSequence.py
itng/signal_processing.py
itng/statistics.py
itng/synchrony.py
itng-0.1.5.dist-info/DESCRIPTION.rst
itng-0.1.5.dist-info/METADATA
itng-0.1.5.dist-info/RECORD
itng-0.1.5.dist-info/WHEEL
itng-0.1.5.dist-info/metadata.json
itng-0.1.5.dist-info/top_level.txt
