Metadata-Version: 2.0
Name: itng
Version: 0.1.5
Summary: Institute for Advanced Studies in Basic Sciences (IASBS) theoretical neuroscience group toolbox.
Home-page: https://github.com/Ziaeemehr/itng_toolbox
Author: Abolfazl Ziaeemehr
Author-email: a.ziaeemehr@gmail.com
License: UNKNOWN
Platform: UNKNOWN
Classifier: Programming Language :: Python :: 3
Classifier: License :: OSI Approved :: MIT License
Classifier: Operating System :: OS Independent
Requires-Python: >=3.1
